[
  {
    "Id": 1,
    "name": "Casual Cotton T-Shirt",
    "brand": "Nike",
    "price": 1299,
    "discountPrice": 899,
    "saleEndTime": "12/20/2024 11:59:59 PM",
    "images": [
      "https://images.unsplash.com/photo-1521572163474-6864f9cf17ab?w=500&h=600&fit=crop",
      "https://images.unsplash.com/photo-1583743814966-8936f37f4ad2?w=500&h=600&fit=crop",
      "https://images.unsplash.com/photo-1586790170083-2f9ceadc732d?w=500&h=600&fit=crop"
    ],
    "sizes": ["S", "M", "L", "XL"],
    "colors": ["Blue", "Black", "White"],
    "category": "men",
    "subcategory": "Topwear",
    "inStock": true
  },
  {
    "Id": 2,
    "name": "Slim Fit Jeans",
    "brand": "Zara",
    "price": 2499,
    "discountPrice": null,
    "images": [
      "https://images.unsplash.com/photo-1542272604-787c3835535d?w=500&h=600&fit=crop",
      "https://images.unsplash.com/photo-1594633312681-425c7b97ccd1?w=500&h=600&fit=crop"
    ],
    "sizes": ["28", "30", "32", "34"],
    "colors": ["Black", "Blue", "Grey"],
    "category": "men",
    "subcategory": "Bottomwear",
    "inStock": true
  },
{
    "Id": 3,
    "name": "Floral Print Dress",
    "brand": "H&M",
    "price": 1899,
    "discountPrice": 1299,
    "saleEndTime": "2024-12-18T12:00:00Z",
    "images": [
      "https://images.unsplash.com/photo-1595777457583-95e059d581b8?w=500&h=600&fit=crop",
      "https://images.unsplash.com/photo-1594633312681-425c7b97ccd1?w=500&h=600&fit=crop"
    ],
    "sizes": ["XS", "S", "M", "L"],
    "colors": ["Pink", "Yellow", "Blue"],
    "category": "women",
    "subcategory": "Dresses",
    "inStock": true
  },
{
    "Id": 4,
    "name": "Leather Jacket",
    "brand": "Zara",
    "price": 4999,
    "discountPrice": 3499,
    "saleEndTime": "2024-12-22T18:30:00Z",
    "images": [
      "https://images.unsplash.com/photo-1551028719-00167b16eac5?w=500&h=600&fit=crop",
      "https://images.unsplash.com/photo-1594633312681-425c7b97ccd1?w=500&h=600&fit=crop"
    ],
    "sizes": ["S", "M", "L", "XL"],
    "colors": ["Black", "Brown"],
    "category": "women",
    "subcategory": "Outerwear",
    "inStock": true
  },
{
    "Id": 5,
    "name": "Running Sneakers",
    "brand": "Adidas",
    "price": 3999,
    "discountPrice": 2999,
    "saleEndTime": "2024-12-17T08:00:00Z",
    "images": [
      "https://images.unsplash.com/photo-1542291026-7eec264c27ff?w=500&h=600&fit=crop",
      "https://images.unsplash.com/photo-1594633312681-425c7b97ccd1?w=500&h=600&fit=crop"
    ],
    "sizes": ["7", "8", "9", "10", "11"],
    "colors": ["White", "Black", "Red"],
    "category": "men",
    "subcategory": "Footwear",
    "inStock": true
  },
{
    "Id": 6,
    "name": "Midi Skirt",
    "brand": "Forever 21",
    "price": 1299,
    "discountPrice": 799,
    "saleEndTime": "2024-12-19T15:45:00Z",
    "images": [
      "https://images.unsplash.com/photo-1594633312681-425c7b97ccd1?w=500&h=600&fit=crop",
      "https://images.unsplash.com/photo-1583743814966-8936f37f4ad2?w=500&h=600&fit=crop"
    ],
    "sizes": ["XS", "S", "M", "L"],
    "colors": ["Black", "Navy", "Brown"],
    "category": "women",
    "subcategory": "Bottomwear",
    "inStock": true
  },
  {
    "Id": 7,
    "name": "Formal Shirt",
    "brand": "Uniqlo",
    "price": 1799,
    "discountPrice": null,
    "images": [
      "https://images.unsplash.com/photo-1602810318383-e386cc2a3ccf?w=500&h=600&fit=crop",
      "https://images.unsplash.com/photo-1594633312681-425c7b97ccd1?w=500&h=600&fit=crop"
    ],
    "sizes": ["S", "M", "L", "XL"],
    "colors": ["White", "Blue", "Pink"],
    "category": "men",
    "subcategory": "Topwear",
    "inStock": true
  },
{
    "Id": 8,
    "name": "Summer Sandals",
    "brand": "Forever 21",
    "price": 999,
    "discountPrice": 699,
    "saleEndTime": "2024-12-21T20:00:00Z",
    "images": [
      "https://images.unsplash.com/photo-1603808033192-082d6919d3e1?w=500&h=600&fit=crop",
      "https://images.unsplash.com/photo-1594633312681-425c7b97ccd1?w=500&h=600&fit=crop"
    ],
    "sizes": ["5", "6", "7", "8", "9"],
    "colors": ["Tan", "Black", "White"],
    "category": "women",
    "subcategory": "Footwear",
    "inStock": true
  },
  {
    "Id": 9,
    "name": "Kids Cotton Pajamas",
    "brand": "H&M",
    "price": 799,
    "discountPrice": 599,
    "images": [
      "https://images.unsplash.com/photo-1596755389378-c31d21fd1273?w=500&h=600&fit=crop",
      "https://images.unsplash.com/photo-1594633312681-425c7b97ccd1?w=500&h=600&fit=crop"
    ],
    "sizes": ["2-3Y", "4-5Y", "6-7Y", "8-9Y"],
    "colors": ["Pink", "Blue", "Yellow"],
    "category": "kids",
    "subcategory": "Sleepwear",
    "inStock": true
  },
  {
    "Id": 10,
    "name": "Kids Denim Jacket",
    "brand": "Zara",
    "price": 1499,
    "discountPrice": 999,
    "images": [
      "https://images.unsplash.com/photo-1515372039744-b8f02a3ae446?w=500&h=600&fit=crop",
      "https://images.unsplash.com/photo-1594633312681-425c7b97ccd1?w=500&h=600&fit=crop"
    ],
    "sizes": ["4-5Y", "6-7Y", "8-9Y", "10-11Y"],
    "colors": ["Blue", "Black"],
    "category": "kids",
    "subcategory": "Outerwear",
    "inStock": true
  },
  {
    "Id": 11,
    "name": "Throw Pillow Set",
    "brand": "IKEA",
    "price": 1299,
    "discountPrice": 999,
    "images": [
      "https://images.unsplash.com/photo-1586023492125-27b2c045efd7?w=500&h=600&fit=crop",
      "https://images.unsplash.com/photo-1594633312681-425c7b97ccd1?w=500&h=600&fit=crop"
    ],
    "sizes": ["16x16", "18x18", "20x20"],
    "colors": ["Grey", "Blue", "Pink"],
    "category": "home",
    "subcategory": "Decor",
    "inStock": true
  },
  {
    "Id": 12,
    "name": "Ceramic Vase",
    "brand": "West Elm",
    "price": 899,
    "discountPrice": null,
    "images": [
      "https://images.unsplash.com/photo-1578662996442-48f60103fc96?w=500&h=600&fit=crop",
      "https://images.unsplash.com/photo-1594633312681-425c7b97ccd1?w=500&h=600&fit=crop"
    ],
    "sizes": ["Small", "Medium", "Large"],
    "colors": ["White", "Terracotta", "Black"],
    "category": "home",
    "subcategory": "Decor",
    "inStock": true
  },
  {
    "Id": 13,
    "name": "Moisturizing Face Cream",
    "brand": "The Ordinary",
    "price": 699,
    "discountPrice": 499,
    "images": [
      "https://images.unsplash.com/photo-1556228720-195a672e8a03?w=500&h=600&fit=crop",
      "https://images.unsplash.com/photo-1594633312681-425c7b97ccd1?w=500&h=600&fit=crop"
    ],
    "sizes": ["30ml", "50ml", "100ml"],
    "colors": ["Clear"],
    "category": "beauty",
    "subcategory": "Skincare",
    "inStock": true
  },
  {
    "Id": 14,
    "name": "Matte Lipstick",
    "brand": "MAC",
    "price": 1299,
    "discountPrice": 999,
    "images": [
      "https://images.unsplash.com/photo-1596462502278-27bfdc403348?w=500&h=600&fit=crop",
      "https://images.unsplash.com/photo-1594633312681-425c7b97ccd1?w=500&h=600&fit=crop"
    ],
    "sizes": ["3g"],
    "colors": ["Red", "Pink", "Brown"],
    "category": "beauty",
    "subcategory": "Makeup",
    "inStock": true
  },
  {
    "Id": 15,
    "name": "Wireless Earbuds",
    "brand": "Apple",
    "price": 12999,
    "discountPrice": 9999,
    "images": [
      "https://images.unsplash.com/photo-1606220945770-b5b6c2c55bf1?w=500&h=600&fit=crop",
      "https://images.unsplash.com/photo-1594633312681-425c7b97ccd1?w=500&h=600&fit=crop"
    ],
    "sizes": ["One Size"],
    "colors": ["White", "Black"],
    "category": "men",
    "subcategory": "Accessories",
    "inStock": true
  },
  {
    "Id": 16,
    "name": "Crossbody Bag",
    "brand": "Coach",
    "price": 8999,
    "discountPrice": 6999,
    "images": [
      "https://images.unsplash.com/photo-1553062407-98eeb64c6a62?w=500&h=600&fit=crop",
      "https://images.unsplash.com/photo-1594633312681-425c7b97ccd1?w=500&h=600&fit=crop"
    ],
    "sizes": ["One Size"],
    "colors": ["Black", "Brown", "Red"],
    "category": "women",
    "subcategory": "Accessories",
    "inStock": true
  },
  {
    "Id": 17,
    "name": "School Backpack",
    "brand": "JanSport",
    "price": 1999,
    "discountPrice": 1499,
    "images": [
      "https://images.unsplash.com/photo-1553062407-98eeb64c6a62?w=500&h=600&fit=crop",
      "https://images.unsplash.com/photo-1594633312681-425c7b97ccd1?w=500&h=600&fit=crop"
    ],
    "sizes": ["One Size"],
    "colors": ["Blue", "Pink", "Black"],
    "category": "kids",
    "subcategory": "Accessories",
    "inStock": true
  },
  {
    "Id": 18,
    "name": "Table Lamp",
    "brand": "IKEA",
    "price": 1499,
    "discountPrice": 1199,
    "images": [
      "https://images.unsplash.com/photo-1507003211169-0a1dd7228f2d?w=500&h=600&fit=crop",
      "https://images.unsplash.com/photo-1594633312681-425c7b97ccd1?w=500&h=600&fit=crop"
    ],
    "sizes": ["One Size"],
    "colors": ["White", "Black", "Gold"],
    "category": "home",
    "subcategory": "Lighting",
    "inStock": true
  },
  {
    "Id": 19,
    "name": "Hair Serum",
    "brand": "L'Oreal",
    "price": 899,
    "discountPrice": 699,
    "images": [
      "https://images.unsplash.com/photo-1556228720-195a672e8a03?w=500&h=600&fit=crop",
      "https://images.unsplash.com/photo-1594633312681-425c7b97ccd1?w=500&h=600&fit=crop"
    ],
    "sizes": ["50ml", "100ml"],
    "colors": ["Clear"],
    "category": "beauty",
    "subcategory": "Haircare",
    "inStock": true
  },
  {
    "Id": 20,
    "name": "Casual Blazer",
    "brand": "Zara",
    "price": 3499,
    "discountPrice": 2499,
    "images": [
      "https://images.unsplash.com/photo-1594633312681-425c7b97ccd1?w=500&h=600&fit=crop",
      "https://images.unsplash.com/photo-1583743814966-8936f37f4ad2?w=500&h=600&fit=crop"
    ],
    "sizes": ["S", "M", "L", "XL"],
    "colors": ["Navy", "Grey", "Black"],
    "category": "women",
"subcategory": "Outerwear",
    "inStock": true
  },
  {
    "Id": 21,
    "name": "Athletic Shorts",
    "brand": "Nike",
    "price": 1599,
    "discountPrice": 1199,
    "images": [
      "https://images.unsplash.com/photo-1594633312681-425c7b97ccd1?w=500&h=600&fit=crop",
      "https://images.unsplash.com/photo-1583743814966-8936f37f4ad2?w=500&h=600&fit=crop"
    ],
    "sizes": ["S", "M", "L", "XL"],
    "colors": ["Black", "Navy", "Grey"],
    "category": "men",
    "subcategory": "Activewear",
    "inStock": true
  },
  {
    "Id": 22,
    "name": "Polo Shirt",
    "brand": "Ralph Lauren",
    "price": 2299,
    "discountPrice": null,
    "images": [
      "https://images.unsplash.com/photo-1602810318383-e386cc2a3ccf?w=500&h=600&fit=crop",
      "https://images.unsplash.com/photo-1594633312681-425c7b97ccd1?w=500&h=600&fit=crop"
    ],
    "sizes": ["S", "M", "L", "XL"],
    "colors": ["White", "Navy", "Red"],
    "category": "men",
    "subcategory": "Topwear",
    "inStock": true
  },
  {
    "Id": 23,
    "name": "Dress Pants",
    "brand": "Hugo Boss",
    "price": 3299,
    "discountPrice": 2499,
    "images": [
      "https://images.unsplash.com/photo-1594633312681-425c7b97ccd1?w=500&h=600&fit=crop",
      "https://images.unsplash.com/photo-1583743814966-8936f37f4ad2?w=500&h=600&fit=crop"
    ],
    "sizes": ["30", "32", "34", "36"],
    "colors": ["Black", "Navy", "Charcoal"],
    "category": "men",
    "subcategory": "Bottomwear",
    "inStock": true
  },
  {
    "Id": 24,
    "name": "Leather Wallet",
    "brand": "Tommy Hilfiger",
    "price": 1899,
    "discountPrice": 1399,
    "images": [
      "https://images.unsplash.com/photo-1553062407-98eeb64c6a62?w=500&h=600&fit=crop",
      "https://images.unsplash.com/photo-1594633312681-425c7b97ccd1?w=500&h=600&fit=crop"
    ],
    "sizes": ["One Size"],
    "colors": ["Black", "Brown", "Tan"],
    "category": "men",
    "subcategory": "Accessories",
    "inStock": true
  },
  {
    "Id": 25,
    "name": "Casual Loafers",
    "brand": "Clarks",
    "price": 4599,
    "discountPrice": 3299,
    "images": [
      "https://images.unsplash.com/photo-1542291026-7eec264c27ff?w=500&h=600&fit=crop",
      "https://images.unsplash.com/photo-1594633312681-425c7b97ccd1?w=500&h=600&fit=crop"
    ],
    "sizes": ["7", "8", "9", "10", "11"],
    "colors": ["Brown", "Black", "Navy"],
    "category": "men",
    "subcategory": "Footwear",
    "inStock": true
  },
  {
    "Id": 26,
    "name": "Cardigan Sweater",
    "brand": "Zara",
    "price": 2799,
    "discountPrice": 1999,
    "images": [
      "https://images.unsplash.com/photo-1594633312681-425c7b97ccd1?w=500&h=600&fit=crop",
      "https://images.unsplash.com/photo-1583743814966-8936f37f4ad2?w=500&h=600&fit=crop"
    ],
    "sizes": ["XS", "S", "M", "L"],
    "colors": ["Beige", "Pink", "Grey"],
    "category": "women",
    "subcategory": "Topwear",
    "inStock": true
  },
  {
    "Id": 27,
    "name": "High-Waisted Jeans",
    "brand": "Levi's",
    "price": 3199,
    "discountPrice": 2399,
    "images": [
      "https://images.unsplash.com/photo-1542272604-787c3835535d?w=500&h=600&fit=crop",
      "https://images.unsplash.com/photo-1594633312681-425c7b97ccd1?w=500&h=600&fit=crop"
    ],
    "sizes": ["26", "28", "30", "32"],
    "colors": ["Blue", "Black", "Light Blue"],
    "category": "women",
    "subcategory": "Bottomwear",
    "inStock": true
  },
  {
    "Id": 28,
    "name": "Evening Clutch",
    "brand": "Michael Kors",
    "price": 5999,
    "discountPrice": 4299,
    "images": [
      "https://images.unsplash.com/photo-1553062407-98eeb64c6a62?w=500&h=600&fit=crop",
      "https://images.unsplash.com/photo-1594633312681-425c7b97ccd1?w=500&h=600&fit=crop"
    ],
    "sizes": ["One Size"],
    "colors": ["Gold", "Silver", "Black"],
    "category": "women",
    "subcategory": "Accessories",
    "inStock": true
  },
  {
    "Id": 29,
    "name": "Ankle Boots",
    "brand": "Steve Madden",
    "price": 3799,
    "discountPrice": 2799,
    "images": [
      "https://images.unsplash.com/photo-1603808033192-082d6919d3e1?w=500&h=600&fit=crop",
      "https://images.unsplash.com/photo-1594633312681-425c7b97ccd1?w=500&h=600&fit=crop"
    ],
    "sizes": ["5", "6", "7", "8", "9"],
    "colors": ["Black", "Brown", "Tan"],
    "category": "women",
    "subcategory": "Footwear",
    "inStock": true
  },
  {
    "Id": 30,
    "name": "Wrap Dress",
    "brand": "Mango",
    "price": 2399,
    "discountPrice": 1799,
    "images": [
      "https://images.unsplash.com/photo-1595777457583-95e059d581b8?w=500&h=600&fit=crop",
      "https://images.unsplash.com/photo-1594633312681-425c7b97ccd1?w=500&h=600&fit=crop"
    ],
    "sizes": ["XS", "S", "M", "L"],
    "colors": ["Red", "Blue", "Green"],
    "category": "women",
    "subcategory": "Dresses",
    "inStock": true
  },
  {
    "Id": 31,
    "name": "Kids Sneakers",
    "brand": "Adidas",
    "price": 1999,
    "discountPrice": 1499,
    "images": [
      "https://images.unsplash.com/photo-1542291026-7eec264c27ff?w=500&h=600&fit=crop",
      "https://images.unsplash.com/photo-1594633312681-425c7b97ccd1?w=500&h=600&fit=crop"
    ],
    "sizes": ["10", "11", "12", "13", "1"],
    "colors": ["White", "Pink", "Blue"],
    "category": "kids",
    "subcategory": "Footwear",
    "inStock": true
  },
  {
    "Id": 32,
    "name": "Graphic T-Shirt",
    "brand": "Disney",
    "price": 899,
    "discountPrice": 699,
    "images": [
      "https://images.unsplash.com/photo-1521572163474-6864f9cf17ab?w=500&h=600&fit=crop",
      "https://images.unsplash.com/photo-1594633312681-425c7b97ccd1?w=500&h=600&fit=crop"
    ],
    "sizes": ["2-3Y", "4-5Y", "6-7Y", "8-9Y"],
    "colors": ["Red", "Blue", "Yellow"],
    "category": "kids",
    "subcategory": "Topwear",
    "inStock": true
  },
  {
    "Id": 33,
    "name": "Play Shorts",
    "brand": "Carter's",
    "price": 699,
    "discountPrice": 499,
    "images": [
      "https://images.unsplash.com/photo-1594633312681-425c7b97ccd1?w=500&h=600&fit=crop",
      "https://images.unsplash.com/photo-1583743814966-8936f37f4ad2?w=500&h=600&fit=crop"
    ],
    "sizes": ["2-3Y", "4-5Y", "6-7Y", "8-9Y"],
    "colors": ["Blue", "Green", "Red"],
    "category": "kids",
    "subcategory": "Bottomwear",
    "inStock": true
  },
  {
    "Id": 34,
    "name": "Winter Jacket",
    "brand": "North Face",
    "price": 2999,
    "discountPrice": 2199,
    "images": [
      "https://images.unsplash.com/photo-1515372039744-b8f02a3ae446?w=500&h=600&fit=crop",
      "https://images.unsplash.com/photo-1594633312681-425c7b97ccd1?w=500&h=600&fit=crop"
    ],
    "sizes": ["4-5Y", "6-7Y", "8-9Y", "10-11Y"],
    "colors": ["Navy", "Pink", "Green"],
    "category": "kids",
    "subcategory": "Outerwear",
    "inStock": true
  },
  {
    "Id": 35,
    "name": "Lunch Box",
    "brand": "Bentgo",
    "price": 1199,
    "discountPrice": 899,
    "images": [
      "https://images.unsplash.com/photo-1553062407-98eeb64c6a62?w=500&h=600&fit=crop",
      "https://images.unsplash.com/photo-1594633312681-425c7b97ccd1?w=500&h=600&fit=crop"
    ],
    "sizes": ["One Size"],
    "colors": ["Blue", "Pink", "Green"],
    "category": "kids",
    "subcategory": "Accessories",
    "inStock": true
  },
  {
    "Id": 36,
    "name": "Coffee Table",
    "brand": "West Elm",
    "price": 8999,
    "discountPrice": 6999,
    "images": [
      "https://images.unsplash.com/photo-1507003211169-0a1dd7228f2d?w=500&h=600&fit=crop",
      "https://images.unsplash.com/photo-1594633312681-425c7b97ccd1?w=500&h=600&fit=crop"
    ],
    "sizes": ["48x24", "60x30"],
    "colors": ["Walnut", "Oak", "Black"],
    "category": "home",
    "subcategory": "Furniture",
    "inStock": true
  },
  {
    "Id": 37,
    "name": "Kitchen Utensil Set",
    "brand": "OXO",
    "price": 2499,
    "discountPrice": 1899,
    "images": [
      "https://images.unsplash.com/photo-1578662996442-48f60103fc96?w=500&h=600&fit=crop",
      "https://images.unsplash.com/photo-1594633312681-425c7b97ccd1?w=500&h=600&fit=crop"
    ],
    "sizes": ["One Size"],
    "colors": ["Stainless Steel", "Black"],
    "category": "home",
    "subcategory": "Kitchen",
    "inStock": true
  },
  {
    "Id": 38,
    "name": "Wall Art Print",
    "brand": "Society6",
    "price": 1599,
    "discountPrice": 1199,
    "images": [
      "https://images.unsplash.com/photo-1586023492125-27b2c045efd7?w=500&h=600&fit=crop",
      "https://images.unsplash.com/photo-1594633312681-425c7b97ccd1?w=500&h=600&fit=crop"
    ],
    "sizes": ["16x20", "20x24", "24x36"],
    "colors": ["Multicolor"],
    "category": "home",
    "subcategory": "Decor",
    "inStock": true
  },
  {
    "Id": 39,
    "name": "Floor Lamp",
    "brand": "CB2",
    "price": 3499,
    "discountPrice": 2799,
    "images": [
      "https://images.unsplash.com/photo-1507003211169-0a1dd7228f2d?w=500&h=600&fit=crop",
      "https://images.unsplash.com/photo-1594633312681-425c7b97ccd1?w=500&h=600&fit=crop"
    ],
    "sizes": ["One Size"],
    "colors": ["Brass", "Black", "White"],
    "category": "home",
    "subcategory": "Lighting",
    "inStock": true
  },
  {
    "Id": 40,
    "name": "Area Rug",
    "brand": "Rugs USA",
    "price": 4999,
    "discountPrice": 3499,
    "images": [
      "https://images.unsplash.com/photo-1586023492125-27b2c045efd7?w=500&h=600&fit=crop",
      "https://images.unsplash.com/photo-1594633312681-425c7b97ccd1?w=500&h=600&fit=crop"
    ],
    "sizes": ["5x7", "8x10", "9x12"],
    "colors": ["Beige", "Grey", "Blue"],
    "category": "home",
    "subcategory": "Decor",
    "inStock": true
  },
  {
    "Id": 41,
    "name": "Vitamin C Serum",
    "brand": "Skinceuticals",
    "price": 1999,
    "discountPrice": 1499,
    "images": [
      "https://images.unsplash.com/photo-1556228720-195a672e8a03?w=500&h=600&fit=crop",
      "https://images.unsplash.com/photo-1594633312681-425c7b97ccd1?w=500&h=600&fit=crop"
    ],
    "sizes": ["30ml"],
    "colors": ["Clear"],
    "category": "beauty",
    "subcategory": "Skincare",
    "inStock": true
  },
  {
    "Id": 42,
    "name": "Foundation",
    "brand": "Fenty Beauty",
    "price": 2499,
    "discountPrice": 1999,
    "images": [
      "https://images.unsplash.com/photo-1596462502278-27bfdc403348?w=500&h=600&fit=crop",
      "https://images.unsplash.com/photo-1594633312681-425c7b97ccd1?w=500&h=600&fit=crop"
    ],
    "sizes": ["32ml"],
    "colors": ["Light", "Medium", "Dark"],
    "category": "beauty",
    "subcategory": "Makeup",
    "inStock": true
  },
  {
    "Id": 43,
    "name": "Shampoo",
    "brand": "Olaplex",
    "price": 1799,
    "discountPrice": 1399,
    "images": [
      "https://images.unsplash.com/photo-1556228720-195a672e8a03?w=500&h=600&fit=crop",
      "https://images.unsplash.com/photo-1594633312681-425c7b97ccd1?w=500&h=600&fit=crop"
    ],
    "sizes": ["250ml", "500ml"],
    "colors": ["Clear"],
    "category": "beauty",
    "subcategory": "Haircare",
    "inStock": true
  },
  {
    "Id": 44,
    "name": "Eye Cream",
    "brand": "Kiehl's",
    "price": 2299,
    "discountPrice": 1799,
    "images": [
      "https://images.unsplash.com/photo-1556228720-195a672e8a03?w=500&h=600&fit=crop",
      "https://images.unsplash.com/photo-1594633312681-425c7b97ccd1?w=500&h=600&fit=crop"
    ],
    "sizes": ["15ml"],
    "colors": ["Clear"],
    "category": "beauty",
    "subcategory": "Skincare",
    "inStock": true
  },
  {
    "Id": 45,
    "name": "Eyeshadow Palette",
    "brand": "Urban Decay",
    "price": 3299,
    "discountPrice": 2499,
    "images": [
      "https://images.unsplash.com/photo-1596462502278-27bfdc403348?w=500&h=600&fit=crop",
      "https://images.unsplash.com/photo-1594633312681-425c7b97ccd1?w=500&h=600&fit=crop"
    ],
    "sizes": ["One Size"],
    "colors": ["Neutral", "Smoky", "Colorful"],
    "category": "beauty",
    "subcategory": "Makeup",
    "inStock": true
  },
  {
    "Id": 46,
    "name": "Hoodie",
    "brand": "Champion",
    "price": 2199,
    "discountPrice": 1599,
    "images": [
      "https://images.unsplash.com/photo-1521572163474-6864f9cf17ab?w=500&h=600&fit=crop",
      "https://images.unsplash.com/photo-1594633312681-425c7b97ccd1?w=500&h=600&fit=crop"
    ],
    "sizes": ["S", "M", "L", "XL"],
    "colors": ["Grey", "Black", "Navy"],
    "category": "men",
    "subcategory": "Topwear",
    "inStock": true
  },
  {
    "Id": 47,
    "name": "Maxi Dress",
    "brand": "Free People",
    "price": 3799,
    "discountPrice": 2899,
    "images": [
      "https://images.unsplash.com/photo-1595777457583-95e059d581b8?w=500&h=600&fit=crop",
      "https://images.unsplash.com/photo-1594633312681-425c7b97ccd1?w=500&h=600&fit=crop"
    ],
    "sizes": ["XS", "S", "M", "L"],
    "colors": ["Floral", "Solid Blue", "Black"],
    "category": "women",
    "subcategory": "Dresses",
    "inStock": true
  },
  {
    "Id": 48,
    "name": "Rain Boots",
    "brand": "Hunter",
    "price": 1299,
    "discountPrice": 999,
    "images": [
      "https://images.unsplash.com/photo-1603808033192-082d6919d3e1?w=500&h=600&fit=crop",
      "https://images.unsplash.com/photo-1594633312681-425c7b97ccd1?w=500&h=600&fit=crop"
    ],
    "sizes": ["10", "11", "12", "13"],
    "colors": ["Yellow", "Red", "Blue"],
    "category": "kids",
    "subcategory": "Footwear",
    "inStock": true
  },
  {
    "Id": 49,
    "name": "Bookshelf",
    "brand": "IKEA",
    "price": 3999,
    "discountPrice": 2999,
    "images": [
      "https://images.unsplash.com/photo-1507003211169-0a1dd7228f2d?w=500&h=600&fit=crop",
      "https://images.unsplash.com/photo-1594633312681-425c7b97ccd1?w=500&h=600&fit=crop"
    ],
    "sizes": ["3-Tier", "4-Tier", "5-Tier"],
    "colors": ["White", "Oak", "Black"],
    "category": "home",
    "subcategory": "Furniture",
    "inStock": true
  },
  {
    "Id": 50,
    "name": "Mascara",
    "brand": "Maybelline",
    "price": 899,
    "discountPrice": 699,
    "images": [
      "https://images.unsplash.com/photo-1596462502278-27bfdc403348?w=500&h=600&fit=crop",
      "https://images.unsplash.com/photo-1594633312681-425c7b97ccd1?w=500&h=600&fit=crop"
    ],
    "sizes": ["One Size"],
    "colors": ["Black", "Brown"],
"category": "beauty",
    "subcategory": "Makeup",
    "inStock": true
  },
  {
    "Id": 51,
    "name": "Silk Blouse",
    "brand": "Zara",
    "price": 2999,
    "discountPrice": 2199,
    "saleEndTime": "2024-12-25T14:30:00Z",
    "images": [
      "https://images.unsplash.com/photo-1594633312681-425c7b97ccd1?w=500&h=600&fit=crop",
      "https://images.unsplash.com/photo-1583743814966-8936f37f4ad2?w=500&h=600&fit=crop"
    ],
    "sizes": ["XS", "S", "M", "L", "XL"],
    "colors": ["Cream", "Navy", "Burgundy"],
    "category": "women",
    "subcategory": "Topwear",
    "inStock": true
  },
  {
    "Id": 52,
    "name": "High-Waisted Leggings",
    "brand": "Lululemon",
    "price": 1899,
    "discountPrice": 1399,
    "saleEndTime": "2024-12-23T10:00:00Z",
    "images": [
      "https://images.unsplash.com/photo-1506629905061-6d4783eb9f2d?w=500&h=600&fit=crop",
      "https://images.unsplash.com/photo-1594633312681-425c7b97ccd1?w=500&h=600&fit=crop"
    ],
    "sizes": ["XS", "S", "M", "L", "XL"],
    "colors": ["Black", "Grey", "Navy"],
    "category": "women",
    "subcategory": "Bottomwear",
    "inStock": true
  },
  {
    "Id": 53,
    "name": "Cocktail Dress",
    "brand": "Mango",
    "price": 4299,
    "discountPrice": 3199,
    "saleEndTime": "2024-12-26T20:00:00Z",
    "images": [
      "https://images.unsplash.com/photo-1595777457583-95e059d581b8?w=500&h=600&fit=crop",
      "https://images.unsplash.com/photo-1566479179817-c9b8ba9e0e1f?w=500&h=600&fit=crop"
    ],
    "sizes": ["XS", "S", "M", "L"],
    "colors": ["Black", "Emerald", "Navy"],
    "category": "women",
    "subcategory": "Dresses",
    "inStock": true
  },
  {
    "Id": 54,
    "name": "Block Heel Pumps",
    "brand": "Nine West",
    "price": 3199,
    "discountPrice": null,
    "images": [
      "https://images.unsplash.com/photo-1603808033192-082d6919d3e1?w=500&h=600&fit=crop",
      "https://images.unsplash.com/photo-1594633312681-425c7b97ccd1?w=500&h=600&fit=crop"
    ],
    "sizes": ["5", "6", "7", "8", "9", "10"],
    "colors": ["Black", "Nude", "Red"],
    "category": "women",
    "subcategory": "Footwear",
    "inStock": true
  },
  {
    "Id": 55,
    "name": "Statement Necklace",
    "brand": "Pandora",
    "price": 2799,
    "discountPrice": 1999,
    "saleEndTime": "2024-12-24T16:45:00Z",
    "images": [
      "https://images.unsplash.com/photo-1515562141207-7a88fb7ce338?w=500&h=600&fit=crop",
      "https://images.unsplash.com/photo-1594633312681-425c7b97ccd1?w=500&h=600&fit=crop"
    ],
    "sizes": ["One Size"],
    "colors": ["Gold", "Silver", "Rose Gold"],
    "category": "women",
    "subcategory": "Accessories",
    "inStock": true
  },
  {
    "Id": 56,
    "name": "Cashmere Sweater",
    "brand": "Uniqlo",
    "price": 3999,
    "discountPrice": 2999,
    "saleEndTime": "2024-12-22T12:00:00Z",
    "images": [
      "https://images.unsplash.com/photo-1594633312681-425c7b97ccd1?w=500&h=600&fit=crop",
      "https://images.unsplash.com/photo-1583743814966-8936f37f4ad2?w=500&h=600&fit=crop"
    ],
    "sizes": ["XS", "S", "M", "L", "XL"],
    "colors": ["Camel", "Pink", "Grey"],
    "category": "women",
    "subcategory": "Topwear",
    "inStock": true
  },
  {
    "Id": 57,
    "name": "Wide-Leg Trousers",
    "brand": "COS",
    "price": 2899,
    "discountPrice": null,
    "images": [
      "https://images.unsplash.com/photo-1594633312681-425c7b97ccd1?w=500&h=600&fit=crop",
      "https://images.unsplash.com/photo-1583743814966-8936f37f4ad2?w=500&h=600&fit=crop"
    ],
    "sizes": ["XS", "S", "M", "L", "XL"],
    "colors": ["Black", "Beige", "Olive"],
    "category": "women",
    "subcategory": "Bottomwear",
    "inStock": true
  },
  {
    "Id": 58,
    "name": "Midi Shirt Dress",
    "brand": "& Other Stories",
    "price": 2199,
    "discountPrice": 1649,
    "saleEndTime": "2024-12-27T09:30:00Z",
    "images": [
      "https://images.unsplash.com/photo-1595777457583-95e059d581b8?w=500&h=600&fit=crop",
      "https://images.unsplash.com/photo-1566479179817-c9b8ba9e0e1f?w=500&h=600&fit=crop"
    ],
    "sizes": ["XS", "S", "M", "L"],
    "colors": ["Striped", "White", "Blue"],
    "category": "women",
    "subcategory": "Dresses",
    "inStock": true
  },
  {
    "Id": 59,
    "name": "Ballet Flats",
    "brand": "Tory Burch",
    "price": 4599,
    "discountPrice": 3299,
    "saleEndTime": "2024-12-21T18:00:00Z",
    "images": [
      "https://images.unsplash.com/photo-1603808033192-082d6919d3e1?w=500&h=600&fit=crop",
      "https://images.unsplash.com/photo-1594633312681-425c7b97ccd1?w=500&h=600&fit=crop"
    ],
    "sizes": ["5", "6", "7", "8", "9", "10"],
    "colors": ["Black", "Tan", "Pink"],
    "category": "women",
    "subcategory": "Footwear",
    "inStock": true
  },
  {
    "Id": 60,
    "name": "Wool Coat",
    "brand": "Massimo Dutti",
    "price": 8999,
    "discountPrice": 6999,
    "saleEndTime": "2024-12-28T15:00:00Z",
    "images": [
      "https://images.unsplash.com/photo-1551028719-00167b16eac5?w=500&h=600&fit=crop",
      "https://images.unsplash.com/photo-1594633312681-425c7b97ccd1?w=500&h=600&fit=crop"
    ],
    "sizes": ["XS", "S", "M", "L", "XL"],
    "colors": ["Camel", "Black", "Grey"],
"category": "women",
    "subcategory": "Outerwear",
    "inStock": true
  },
  {
    "Id": 61,
    "name": "Henley Long Sleeve",
    "brand": "J.Crew",
    "price": 1999,
    "discountPrice": 1499,
    "saleEndTime": "2024-12-29T14:00:00Z",
    "images": [
      "https://images.unsplash.com/photo-1602810318383-e386cc2a3ccf?w=500&h=600&fit=crop",
      "https://images.unsplash.com/photo-1521572163474-6864f9cf17ab?w=500&h=600&fit=crop"
    ],
    "sizes": ["S", "M", "L", "XL", "XXL"],
    "colors": ["Navy", "Grey", "Burgundy"],
    "category": "men",
    "subcategory": "Topwear",
    "inStock": true
  },
  {
    "Id": 62,
    "name": "Cargo Pants",
    "brand": "Dockers",
    "price": 2799,
    "discountPrice": null,
    "images": [
      "https://images.unsplash.com/photo-1594633312681-425c7b97ccd1?w=500&h=600&fit=crop",
      "https://images.unsplash.com/photo-1542272604-787c3835535d?w=500&h=600&fit=crop"
    ],
    "sizes": ["28", "30", "32", "34", "36"],
    "colors": ["Khaki", "Olive", "Black"],
    "category": "men",
    "subcategory": "Bottomwear",
    "inStock": true
  },
  {
    "Id": 63,
    "name": "Oxford Dress Shoes",
    "brand": "Cole Haan",
    "price": 5999,
    "discountPrice": 4299,
    "saleEndTime": "2024-12-30T18:00:00Z",
    "images": [
      "https://images.unsplash.com/photo-1542291026-7eec264c27ff?w=500&h=600&fit=crop",
      "https://images.unsplash.com/photo-1583743814966-8936f37f4ad2?w=500&h=600&fit=crop"
    ],
    "sizes": ["7", "8", "9", "10", "11", "12"],
    "colors": ["Black", "Brown", "Cognac"],
    "category": "men",
    "subcategory": "Footwear",
    "inStock": true
  },
  {
    "Id": 64,
    "name": "Leather Belt",
    "brand": "Fossil",
    "price": 1599,
    "discountPrice": 1199,
    "saleEndTime": "2024-12-31T12:00:00Z",
    "images": [
      "https://images.unsplash.com/photo-1553062407-98eeb64c6a62?w=500&h=600&fit=crop",
      "https://images.unsplash.com/photo-1594633312681-425c7b97ccd1?w=500&h=600&fit=crop"
    ],
    "sizes": ["32", "34", "36", "38", "40"],
    "colors": ["Black", "Brown", "Tan"],
    "category": "men",
    "subcategory": "Accessories",
    "inStock": true
  },
  {
    "Id": 65,
    "name": "Denim Jacket",
    "brand": "Levi's",
    "price": 3499,
    "discountPrice": 2599,
    "saleEndTime": "2024-12-28T20:30:00Z",
    "images": [
      "https://images.unsplash.com/photo-1515372039744-b8f02a3ae446?w=500&h=600&fit=crop",
      "https://images.unsplash.com/photo-1551028719-00167b16eac5?w=500&h=600&fit=crop"
    ],
    "sizes": ["S", "M", "L", "XL", "XXL"],
    "colors": ["Light Blue", "Dark Blue", "Black"],
    "category": "men",
    "subcategory": "Outerwear",
    "inStock": true
  },
  {
    "Id": 66,
    "name": "Performance Tank Top",
    "brand": "Under Armour",
    "price": 1299,
    "discountPrice": 999,
    "images": [
      "https://images.unsplash.com/photo-1521572163474-6864f9cf17ab?w=500&h=600&fit=crop",
      "https://images.unsplash.com/photo-1594633312681-425c7b97ccd1?w=500&h=600&fit=crop"
    ],
    "sizes": ["S", "M", "L", "XL", "XXL"],
    "colors": ["Black", "Grey", "Navy"],
    "category": "men",
    "subcategory": "Activewear",
    "inStock": true
  },
  {
    "Id": 67,
    "name": "Chino Shorts",
    "brand": "Banana Republic",
    "price": 1899,
    "discountPrice": null,
    "images": [
      "https://images.unsplash.com/photo-1594633312681-425c7b97ccd1?w=500&h=600&fit=crop",
      "https://images.unsplash.com/photo-1583743814966-8936f37f4ad2?w=500&h=600&fit=crop"
    ],
    "sizes": ["28", "30", "32", "34", "36"],
    "colors": ["Khaki", "Navy", "Olive"],
    "category": "men",
    "subcategory": "Bottomwear",
    "inStock": true
  },
  {
    "Id": 68,
    "name": "Canvas Sneakers",
    "brand": "Converse",
    "price": 2199,
    "discountPrice": 1649,
    "saleEndTime": "2025-01-02T15:00:00Z",
    "images": [
      "https://images.unsplash.com/photo-1542291026-7eec264c27ff?w=500&h=600&fit=crop",
      "https://images.unsplash.com/photo-1606220945770-b5b6c2c55bf1?w=500&h=600&fit=crop"
    ],
    "sizes": ["7", "8", "9", "10", "11", "12"],
    "colors": ["White", "Black", "Navy"],
    "category": "men",
    "subcategory": "Footwear",
    "inStock": true
  },
  {
    "Id": 69,
    "name": "Baseball Cap",
    "brand": "New Era",
    "price": 999,
    "discountPrice": 799,
    "images": [
      "https://images.unsplash.com/photo-1553062407-98eeb64c6a62?w=500&h=600&fit=crop",
      "https://images.unsplash.com/photo-1594633312681-425c7b97ccd1?w=500&h=600&fit=crop"
    ],
    "sizes": ["One Size"],
    "colors": ["Navy", "Black", "Grey"],
    "category": "men",
    "subcategory": "Accessories",
    "inStock": true
  },
  {
    "Id": 70,
    "name": "Windbreaker Jacket",
    "brand": "Patagonia",
    "price": 4299,
    "discountPrice": 3199,
    "saleEndTime": "2025-01-03T10:00:00Z",
    "images": [
      "https://images.unsplash.com/photo-1515372039744-b8f02a3ae446?w=500&h=600&fit=crop",
      "https://images.unsplash.com/photo-1551028719-00167b16eac5?w=500&h=600&fit=crop"
    ],
    "sizes": ["S", "M", "L", "XL", "XXL"],
    "colors": ["Navy", "Forest Green", "Black"],
    "category": "men",
"category": "men",
    "subcategory": "Outerwear",
    "inStock": true
  },
  {
    "Id": 71,
    "name": "Kids Cartoon T-Shirt",
    "brand": "H&M",
    "price": 699,
    "discountPrice": 549,
    "saleEndTime": "2025-01-05T14:00:00Z",
    "images": [
      "https://images.unsplash.com/photo-1521572163474-6864f9cf17ab?w=500&h=600&fit=crop",
      "https://images.unsplash.com/photo-1596755389378-c31d21fd1273?w=500&h=600&fit=crop"
    ],
    "sizes": ["2-3Y", "4-5Y", "6-7Y", "8-9Y"],
    "colors": ["Blue", "Pink", "Green"],
    "category": "kids",
    "subcategory": "Topwear",
    "inStock": true
  },
  {
    "Id": 72,
    "name": "Kids Hoodie",
    "brand": "Nike",
    "price": 1299,
    "discountPrice": 999,
    "images": [
      "https://images.unsplash.com/photo-1521572163474-6864f9cf17ab?w=500&h=600&fit=crop",
      "https://images.unsplash.com/photo-1596755389378-c31d21fd1273?w=500&h=600&fit=crop"
    ],
    "sizes": ["4-5Y", "6-7Y", "8-9Y", "10-11Y"],
    "colors": ["Navy", "Pink", "Grey"],
    "category": "kids",
    "subcategory": "Topwear",
    "inStock": true
  },
  {
    "Id": 73,
    "name": "Kids Leggings",
    "brand": "Carter's",
    "price": 599,
    "discountPrice": 449,
    "saleEndTime": "2025-01-04T16:30:00Z",
    "images": [
      "https://images.unsplash.com/photo-1594633312681-425c7b97ccd1?w=500&h=600&fit=crop",
      "https://images.unsplash.com/photo-1596755389378-c31d21fd1273?w=500&h=600&fit=crop"
    ],
    "sizes": ["2-3Y", "4-5Y", "6-7Y", "8-9Y"],
    "colors": ["Black", "Purple", "Pink"],
    "category": "kids",
    "subcategory": "Bottomwear",
    "inStock": true
  },
  {
    "Id": 74,
    "name": "Kids Jeans",
    "brand": "Zara",
    "price": 899,
    "discountPrice": null,
    "images": [
      "https://images.unsplash.com/photo-1542272604-787c3835535d?w=500&h=600&fit=crop",
      "https://images.unsplash.com/photo-1596755389378-c31d21fd1273?w=500&h=600&fit=crop"
    ],
    "sizes": ["4-5Y", "6-7Y", "8-9Y", "10-11Y"],
    "colors": ["Blue", "Light Blue", "Black"],
    "category": "kids",
    "subcategory": "Bottomwear",
    "inStock": true
  },
  {
    "Id": 75,
    "name": "Kids Light-Up Sneakers",
    "brand": "Skechers",
    "price": 1799,
    "discountPrice": 1399,
    "saleEndTime": "2025-01-06T12:00:00Z",
    "images": [
      "https://images.unsplash.com/photo-1542291026-7eec264c27ff?w=500&h=600&fit=crop",
      "https://images.unsplash.com/photo-1596755389378-c31d21fd1273?w=500&h=600&fit=crop"
    ],
    "sizes": ["10", "11", "12", "13", "1"],
    "colors": ["Multi", "Pink", "Blue"],
    "category": "kids",
    "subcategory": "Footwear",
    "inStock": true
  },
  {
    "Id": 76,
    "name": "Kids Sundress",
    "brand": "H&M",
    "price": 799,
    "discountPrice": 599,
    "images": [
      "https://images.unsplash.com/photo-1595777457583-95e059d581b8?w=500&h=600&fit=crop",
      "https://images.unsplash.com/photo-1596755389378-c31d21fd1273?w=500&h=600&fit=crop"
    ],
    "sizes": ["2-3Y", "4-5Y", "6-7Y", "8-9Y"],
    "colors": ["Yellow", "Pink", "Blue"],
    "category": "kids",
    "subcategory": "Topwear",
    "inStock": true
  },
  {
    "Id": 77,
    "name": "Kids Sandals",
    "brand": "Crocs",
    "price": 999,
    "discountPrice": 799,
    "saleEndTime": "2025-01-07T18:00:00Z",
    "images": [
      "https://images.unsplash.com/photo-1603808033192-082d6919d3e1?w=500&h=600&fit=crop",
      "https://images.unsplash.com/photo-1596755389378-c31d21fd1273?w=500&h=600&fit=crop"
    ],
    "sizes": ["10", "11", "12", "13", "1"],
    "colors": ["Blue", "Pink", "Green"],
    "category": "kids",
    "subcategory": "Footwear",
    "inStock": true
  },
  {
    "Id": 78,
    "name": "Kids Fleece Jacket",
    "brand": "North Face",
    "price": 1999,
    "discountPrice": 1499,
    "images": [
      "https://images.unsplash.com/photo-1515372039744-b8f02a3ae446?w=500&h=600&fit=crop",
      "https://images.unsplash.com/photo-1596755389378-c31d21fd1273?w=500&h=600&fit=crop"
    ],
    "sizes": ["4-5Y", "6-7Y", "8-9Y", "10-11Y"],
    "colors": ["Navy", "Pink", "Red"],
    "category": "kids",
    "subcategory": "Outerwear",
    "inStock": true
  },
  {
    "Id": 79,
    "name": "Kids Cargo Shorts",
    "brand": "Gap",
    "price": 699,
    "discountPrice": null,
    "images": [
      "https://images.unsplash.com/photo-1594633312681-425c7b97ccd1?w=500&h=600&fit=crop",
      "https://images.unsplash.com/photo-1596755389378-c31d21fd1273?w=500&h=600&fit=crop"
    ],
    "sizes": ["4-5Y", "6-7Y", "8-9Y", "10-11Y"],
    "colors": ["Khaki", "Navy", "Green"],
    "category": "kids",
    "subcategory": "Bottomwear",
    "inStock": true
  },
  {
    "Id": 80,
    "name": "Kids Baseball Cap",
    "brand": "Nike",
    "price": 649,
    "discountPrice": 499,
    "saleEndTime": "2025-01-08T10:30:00Z",
    "images": [
      "https://images.unsplash.com/photo-1553062407-98eeb64c6a62?w=500&h=600&fit=crop",
      "https://images.unsplash.com/photo-1596755389378-c31d21fd1273?w=500&h=600&fit=crop"
    ],
    "sizes": ["One Size"],
    "colors": ["Blue", "Red", "Black"],
    "category": "kids",
    "subcategory": "Accessories",
    "inStock": true
  },
  {
    "Id": 81,
    "name": "Kids Polka Dot Pajamas",
    "brand": "Carter's",
    "price": 899,
    "discountPrice": 699,
    "images": [
      "https://images.unsplash.com/photo-1596755389378-c31d21fd1273?w=500&h=600&fit=crop",
      "https://images.unsplash.com/photo-1521572163474-6864f9cf17ab?w=500&h=600&fit=crop"
    ],
    "sizes": ["2-3Y", "4-5Y", "6-7Y", "8-9Y"],
    "colors": ["Pink", "Blue", "Purple"],
    "category": "kids",
    "subcategory": "Sleepwear",
    "inStock": true
  },
  {
    "Id": 82,
    "name": "Kids Sweatpants",
    "brand": "Adidas",
    "price": 799,
    "discountPrice": 599,
    "saleEndTime": "2025-01-09T14:15:00Z",
    "images": [
      "https://images.unsplash.com/photo-1594633312681-425c7b97ccd1?w=500&h=600&fit=crop",
      "https://images.unsplash.com/photo-1596755389378-c31d21fd1273?w=500&h=600&fit=crop"
    ],
    "sizes": ["4-5Y", "6-7Y", "8-9Y", "10-11Y"],
    "colors": ["Grey", "Navy", "Pink"],
    "category": "kids",
    "subcategory": "Bottomwear",
    "inStock": true
  },
  {
    "Id": 83,
    "name": "Kids Raincoat",
    "brand": "Gap",
    "price": 1299,
    "discountPrice": 999,
    "images": [
      "https://images.unsplash.com/photo-1515372039744-b8f02a3ae446?w=500&h=600&fit=crop",
      "https://images.unsplash.com/photo-1596755389378-c31d21fd1273?w=500&h=600&fit=crop"
    ],
    "sizes": ["4-5Y", "6-7Y", "8-9Y", "10-11Y"],
    "colors": ["Yellow", "Blue", "Pink"],
    "category": "kids",
    "subcategory": "Outerwear",
    "inStock": true
  },
  {
    "Id": 84,
    "name": "Kids Hair Clips Set",
    "brand": "Claire's",
    "price": 399,
    "discountPrice": 299,
    "saleEndTime": "2025-01-10T11:00:00Z",
    "images": [
      "https://images.unsplash.com/photo-1553062407-98eeb64c6a62?w=500&h=600&fit=crop",
      "https://images.unsplash.com/photo-1596755389378-c31d21fd1273?w=500&h=600&fit=crop"
    ],
    "sizes": ["One Size"],
    "colors": ["Multi", "Pink", "Purple"],
    "category": "kids",
    "subcategory": "Accessories",
    "inStock": true
  },
  {
    "Id": 85,
    "name": "Kids Ankle Boots",
    "brand": "Timberland",
    "price": 1599,
    "discountPrice": null,
    "images": [
      "https://images.unsplash.com/photo-1603808033192-082d6919d3e1?w=500&h=600&fit=crop",
      "https://images.unsplash.com/photo-1596755389378-c31d21fd1273?w=500&h=600&fit=crop"
    ],
    "sizes": ["10", "11", "12", "13", "1"],
    "colors": ["Brown", "Black", "Pink"],
    "category": "kids",
    "subcategory": "Footwear",
    "inStock": true
  },
  {
    "Id": 86,
    "name": "Kids Striped Shirt",
    "brand": "Gap",
    "price": 649,
    "discountPrice": 489,
    "saleEndTime": "2025-01-11T15:45:00Z",
    "images": [
      "https://images.unsplash.com/photo-1521572163474-6864f9cf17ab?w=500&h=600&fit=crop",
      "https://images.unsplash.com/photo-1596755389378-c31d21fd1273?w=500&h=600&fit=crop"
    ],
    "sizes": ["2-3Y", "4-5Y", "6-7Y", "8-9Y"],
    "colors": ["Navy/White", "Pink/White", "Blue/White"],
    "category": "kids",
    "subcategory": "Topwear",
    "inStock": true
  },
  {
    "Id": 87,
    "name": "Kids Winter Coat",
    "brand": "Columbia",
    "price": 2499,
    "discountPrice": 1899,
    "saleEndTime": "2025-01-12T09:00:00Z",
    "images": [
      "https://images.unsplash.com/photo-1515372039744-b8f02a3ae446?w=500&h=600&fit=crop",
      "https://images.unsplash.com/photo-1596755389378-c31d21fd1273?w=500&h=600&fit=crop"
    ],
    "sizes": ["4-5Y", "6-7Y", "8-9Y", "10-11Y"],
    "colors": ["Navy", "Pink", "Red"],
    "category": "kids",
    "subcategory": "Outerwear",
    "inStock": true
  },
  {
    "Id": 88,
    "name": "Kids Nightgown",
    "brand": "Disney",
    "price": 799,
    "discountPrice": 599,
    "images": [
      "https://images.unsplash.com/photo-1596755389378-c31d21fd1273?w=500&h=600&fit=crop",
      "https://images.unsplash.com/photo-1521572163474-6864f9cf17ab?w=500&h=600&fit=crop"
    ],
    "sizes": ["2-3Y", "4-5Y", "6-7Y", "8-9Y"],
    "colors": ["Pink", "Purple", "Blue"],
    "category": "kids",
    "subcategory": "Sleepwear",
    "inStock": true
  },
  {
    "Id": 89,
    "name": "Kids Mini Backpack",
    "brand": "JanSport",
    "price": 1199,
    "discountPrice": 899,
    "saleEndTime": "2025-01-13T13:20:00Z",
    "images": [
      "https://images.unsplash.com/photo-1553062407-98eeb64c6a62?w=500&h=600&fit=crop",
      "https://images.unsplash.com/photo-1596755389378-c31d21fd1273?w=500&h=600&fit=crop"
    ],
    "sizes": ["One Size"],
    "colors": ["Pink", "Blue", "Purple"],
    "category": "kids",
    "subcategory": "Accessories",
    "inStock": true
  },
  {
    "Id": 90,
    "name": "Kids Canvas Shoes",
    "brand": "Converse",
    "price": 1299,
    "discountPrice": null,
    "images": [
      "https://images.unsplash.com/photo-1542291026-7eec264c27ff?w=500&h=600&fit=crop",
      "https://images.unsplash.com/photo-1596755389378-c31d21fd1273?w=500&h=600&fit=crop"
    ],
    "sizes": ["10", "11", "12", "13", "1"],
    "colors": ["White", "Pink", "Blue"],
    "category": "kids",
    "subcategory": "Footwear",
    "inStock": true
  }